konfitest/__init__.py
konfitest/__main__.py
konfitest-23.11.1.dist-info/LICENSE
konfitest-23.11.1.dist-info/METADATA
konfitest-23.11.1.dist-info/WHEEL
konfitest-23.11.1.dist-info/entry_points.txt
konfitest-23.11.1.dist-info/top_level.txt
konfitest-23.11.1.dist-info/RECORD
