Metadata-Version: 2.1
Name: konfitest
Version: 23.11.1
Summary: Pytest extension to run subset of tests for quick confidence check
License: MIT License
Keywords: pytest,smoke test
Classifier: License :: OSI Approved :: MIT License
Classifier: Programming Language :: Python :: 3
Requires-Python: >=3.9
License-File: LICENSE
Provides-Extra: dev
Requires-Dist: pytest ; extra == 'dev'
